modified_cam_clay/__init__.py
modified_cam_clay/default_params.py
modified_cam_clay/drained.py
modified_cam_clay/modified_cam_clay.py
modified_cam_clay/undrained.py
modified_cam_clay/utils.py
modified_cam_clay-1.0.1.dist-info/LICENSE
modified_cam_clay-1.0.1.dist-info/METADATA
modified_cam_clay-1.0.1.dist-info/WHEEL
modified_cam_clay-1.0.1.dist-info/top_level.txt
modified_cam_clay-1.0.1.dist-info/RECORD
