Metadata-Version: 2.1
Name: modified-cam-clay
Version: 1.0.1
Summary: A model to predict stress-strain behavior of soil
Home-page: https://github.com/QuantumNovice/ModifiedCamClay
Author: Has
Author-email: portabl3lapy@gmail.com
License: UNKNOWN
Project-URL: Bug Tracker, https://github.com/QuantumNovice/ModifiedCamClay/issues
Platform: UNKNOWN
Classifier: Programming Language :: Python :: 3
Classifier: License :: OSI Approved :: MIT License
Classifier: Operating System :: OS Independent
Requires-Python: >=3.6
License-File: LICENSE
Requires-Dist: matplotlib
Requires-Dist: numpy
